django_admin_inline_paginator_plus/__init__.py
django_admin_inline_paginator_plus/admin.py
django_admin_inline_paginator_plus/apps.py
django_admin_inline_paginator_plus/static/django_admin_inline_paginator_plus/paginator.css
django_admin_inline_paginator_plus/templates/admin/paginated_base.html
django_admin_inline_paginator_plus/templates/admin/stacked_paginated.html
django_admin_inline_paginator_plus/templates/admin/stacked_paginator.html
django_admin_inline_paginator_plus/templates/admin/tabular_paginated.html
django_admin_inline_paginator_plus/templates/admin/tabular_paginator.html
django_admin_inline_paginator_plus/templatetags/__init__.py
django_admin_inline_paginator_plus/templatetags/paginated_inline.py
django_admin_inline_paginator_plus-0.1.4.dist-info/licenses/LICENSE
django_admin_inline_paginator_plus-0.1.4.dist-info/METADATA
django_admin_inline_paginator_plus-0.1.4.dist-info/WHEEL
django_admin_inline_paginator_plus-0.1.4.dist-info/top_level.txt
django_admin_inline_paginator_plus-0.1.4.dist-info/RECORD
