Metadata-Version: 2.4
Name: django-admin-inline-paginator-plus
Version: 0.1.4
Summary: The 'Django Admin Inline Paginator Plus' is simple way to paginate your inlines in Django admin
Author-email: Shinneider Libanio da Silva <shinneider-libanio@hotmail.com>, Dmytro Litvinov <me@dmytrolitvinov.com>
Maintainer-email: Dmytro Litvinov <me@dmytrolitvinov.com>
License: MIT
Project-URL: Homepage, https://github.com/DmytroLitvinov/django-admin-inline-paginator-plus
Project-URL: Issues, https://github.com/DmytroLitvinov/django-admin-inline-paginator-plus/issues
Project-URL: Changelog, https://github.com/DmytroLitvinov/django-admin-inline-paginator-plus/blob/master/CHANGELOG.md
Keywords: django,admin,paginator,inlines,pagination
Classifier: Development Status :: 5 - Production/Stable
Classifier: Framework :: Django :: 4.2
Classifier: Framework :: Django :: 5.0
Classifier: Framework :: Django :: 5.1
Classifier: Framework :: Django :: 5.2
Classifier: Environment :: Web Environment
Classifier: Framework :: Django
Classifier: Intended Audience :: Developers
Classifier: License :: OSI Approved :: MIT License
Classifier: Natural Language :: English
Classifier: Operating System :: OS Independent
Classifier: Programming Language :: Python
Classifier: Programming Language :: Python :: 3 :: Only
Classifier: Programming Language :: Python :: 3.9
Classifier: Programming Language :: Python :: 3.10
Classifier: Programming Language :: Python :: 3.11
Classifier: Programming Language :: Python :: 3.12
Classifier: Programming Language :: Python :: 3.13
Classifier: Topic :: Internet :: WWW/HTTP
Classifier: Topic :: Software Development :: Libraries :: Python Modules
Requires-Python: >=3.8
License-File: LICENSE
Requires-Dist: django
Provides-Extra: dev
Requires-Dist: coverage; extra == "dev"
Requires-Dist: mypy; extra == "dev"
Requires-Dist: pytest; extra == "dev"
Requires-Dist: ruff; extra == "dev"
Dynamic: license-file
